multinherit/__init__.py
multinherit/multinherit.py
multinherit/multinherit_example.py
multinherit-0.1.0.dist-info/LICENSE
multinherit-0.1.0.dist-info/METADATA
multinherit-0.1.0.dist-info/WHEEL
multinherit-0.1.0.dist-info/top_level.txt
multinherit-0.1.0.dist-info/RECORD
