Metadata-Version: 2.1
Name: multinherit
Version: 0.1.0
Summary: Package solving problems with super() builtin for classes with multiple inheritance.
Home-page: https://github.com/DovaX/multinherit
Author: DovaX
Author-email: dovax.ai@gmail.com
License: UNKNOWN
Platform: UNKNOWN
Classifier: Programming Language :: Python :: 3
Classifier: License :: OSI Approved :: MIT License
Classifier: Operating System :: OS Independent
Requires-Python: >=3.6
